streamerretriever/__init__.py
streamerretriever/cli.py
streamerretriever/constants.py
streamerretriever/fileoperator.py
streamerretriever/streamerretriever.py
streamerretriever/tools.py
streamerretriever/twitchobjs.py
streamerretriever/twitchrequest.py
Streamer_Retriever-0.20.2.dist-info/LICENSE
Streamer_Retriever-0.20.2.dist-info/METADATA
Streamer_Retriever-0.20.2.dist-info/WHEEL
Streamer_Retriever-0.20.2.dist-info/entry_points.txt
Streamer_Retriever-0.20.2.dist-info/top_level.txt
Streamer_Retriever-0.20.2.dist-info/RECORD
