Metadata-Version: 2.1
Name: Streamer-Retriever
Version: 0.20.2
Summary: Filter Twitch streams that are online from follows text file.
Home-page: https://gitlab.com/obtusescholar/streamerretriever
Author: obtusescholar
License: GPLv3+
Keywords: twitch terminal
Platform: UNKNOWN
Classifier: Development Status :: 3 - Alpha
Classifier: Environment :: Console
Classifier: License :: OSI Approved :: GNU General Public License v3 or later (GPLv3+)
Classifier: Operating System :: OS Independent
Classifier: Intended Audience :: End Users/Desktop
Classifier: Programming Language :: Python :: 3.8
Classifier: Topic :: Internet
Classifier: Topic :: Terminals
Classifier: Topic :: Utilities
Requires-Python: >=3.8
